odoo/addons/website_crm_quick_answer/README.rst
odoo/addons/website_crm_quick_answer/__init__.py
odoo/addons/website_crm_quick_answer/__manifest__.py
odoo/addons/website_crm_quick_answer/data/base_automation_data.xml
odoo/addons/website_crm_quick_answer/i18n/es.po
odoo/addons/website_crm_quick_answer/i18n/es_AR.po
odoo/addons/website_crm_quick_answer/i18n/fr.po
odoo/addons/website_crm_quick_answer/i18n/it.po
odoo/addons/website_crm_quick_answer/i18n/pt_BR.po
odoo/addons/website_crm_quick_answer/i18n/website_crm_quick_answer.pot
odoo/addons/website_crm_quick_answer/readme/CONFIGURE.rst
odoo/addons/website_crm_quick_answer/readme/CONTRIBUTORS.rst
odoo/addons/website_crm_quick_answer/readme/DESCRIPTION.rst
odoo/addons/website_crm_quick_answer/readme/USAGE.rst
odoo/addons/website_crm_quick_answer/static/description/icon.png
odoo/addons/website_crm_quick_answer/static/description/index.html
odoo14_addon_website_crm_quick_answer-14.0.1.1.1.dev12.dist-info/METADATA
odoo14_addon_website_crm_quick_answer-14.0.1.1.1.dev12.dist-info/WHEEL
odoo14_addon_website_crm_quick_answer-14.0.1.1.1.dev12.dist-info/top_level.txt
odoo14_addon_website_crm_quick_answer-14.0.1.1.1.dev12.dist-info/RECORD
